{
  "lastChecks": {
    "email": null,
    "calendar": null,
    "weather": 1745834239,
    "project_status": 1745842800,
    "git_workspace": 1745936994,
    "business": 1745936994,
    "revenue": 1745943860
  },
  "lastProactiveMessage": 1745934000,
  "checksToday": 6,
  "lastNightlyReview": null,
  "notes": "18:04 dimanche - Batch 1 en cours: 2/5 sent (Ferme Val Vert, BioCoop Provence), 3/5 queued (ETA 18:20). 0% bounce. Batch 2 ready (5 producteurs 10/10) pour slot 21h. T-30h deadline. Revenue: 0€/500€. Autonomous execution active."
}
