{
  "lastChecks": {
    "email": null,
    "calendar": null,
    "weather": 1745834239,
    "project_status": 1745842800,
    "git_workspace": 1745867700,
    "business": 1745867700,
    "revenue": 1745867700
  },
  "lastProactiveMessage": 1745860800,
  "checksToday": 10,
  "lastNightlyReview": null,
  "notes": "22:01 - Situation stabilisée: Site UP (ellievai.com accessible), merci.html créé. Batch 1 emails en delivery_delayed (pas bounced, attente 28h). Payment links Stripe = action manuelle requise. Prochaine action autonome: dimanche 10h (prospection batch 2)."
}
